pyteuf/__init__.py
pyteuf/tf_data.py
pyteuf/tf_transforms.py
pyteuf/utils.py
pyteuf/tests/__init__.py
pyteuf/tests/test_tf_data.py
pyteuf/tests/test_tf_transforms.py
pyteuf/tests/test_utils.py
pyteuf-1.0.1.dist-info/DESCRIPTION.rst
pyteuf-1.0.1.dist-info/METADATA
pyteuf-1.0.1.dist-info/RECORD
pyteuf-1.0.1.dist-info/WHEEL
pyteuf-1.0.1.dist-info/metadata.json
pyteuf-1.0.1.dist-info/top_level.txt
